collective.sentry-0.3.2-py3.11-nspkg.pth
collective/sentry/__init__.py
collective/sentry/configure.zcml
collective/sentry/error_handler.py
collective.sentry-0.3.2.dist-info/METADATA
collective.sentry-0.3.2.dist-info/WHEEL
collective.sentry-0.3.2.dist-info/entry_points.txt
collective.sentry-0.3.2.dist-info/namespace_packages.txt
collective.sentry-0.3.2.dist-info/top_level.txt
collective.sentry-0.3.2.dist-info/RECORD
