Metadata-Version: 2.1
Name: collective.sentry
Version: 0.3.2
Summary: Sentry integration with Plone 5.2/Zope 4
Author: Andreas Jung
Author-email: info@zopyx.com
License: GPL
Project-URL: Code, https://github.com/collective/collective.sentry
Project-URL: Tracker, https://github.com/collective/collective.sentry/issues
Keywords: policy
Classifier: Development Status :: 4 - Beta
Classifier: Intended Audience :: Developers
Classifier: License :: OSI Approved :: GNU General Public License (GPL)
Classifier: Programming Language :: Python
Classifier: Programming Language :: Python :: 3.6
Classifier: Programming Language :: Python :: 3.7
Classifier: Programming Language :: Python :: 3.8
Classifier: Programming Language :: Python :: 3.9
Classifier: Programming Language :: Python :: 3.10
Classifier: Programming Language :: Python :: 3.11
Classifier: Framework :: Plone
Classifier: Framework :: Plone :: 5.2
Classifier: Framework :: Plone :: 6.0
Classifier: Framework :: Zope
Classifier: Framework :: Zope :: 4
Classifier: Framework :: Zope :: 5
Classifier: Topic :: Software Development :: Libraries :: Python Modules
Requires-Dist: setuptools
Requires-Dist: sentry-sdk
